mkdocs_dsfr/__init__.py
mkdocs_dsfr/plugin/__init__.py
mkdocs_dsfr/plugin/config.py
mkdocs_dsfr/plugin/link.py
mkdocs_dsfr/plugin/media.py
mkdocs_dsfr/plugin/plugin.py
mkdocs_dsfr/plugin/py.typed
mkdocs_dsfr/plugin/table.py
mkdocs_dsfr/plugin/templates/accordion.html
mkdocs_dsfr/plugin/templates/alert.html
mkdocs_dsfr/plugin/templates/badge.html
mkdocs_dsfr/plugin/templates/callout.html
mkdocs_dsfr/plugin/templates/card.html
mkdocs_dsfr/plugin/templates/highlight.html
mkdocs_dsfr/plugin/templates/icon.html
mkdocs_dsfr/plugin/templates/notice.html
mkdocs_dsfr/plugin/templates/pictogram.html
mkdocs_dsfr/plugin/templates/quote.html
mkdocs_dsfr/plugin/templates/tab.html
mkdocs_dsfr/plugin/templates/tile.html
mkdocs_dsfr/plugin/utils.py
mkdocs_dsfr/theme/404.html
mkdocs_dsfr/theme/__init__.py
mkdocs_dsfr/theme/assets/scripts/highlightjs-import-theme.js
mkdocs_dsfr/theme/assets/styles/dsfr.css
mkdocs_dsfr/theme/assets/styles/highlightjs.css
mkdocs_dsfr/theme/assets/styles/mkdocs-kroki-plugin.css
mkdocs_dsfr/theme/assets/styles/pymdownx-emoji.css
mkdocs_dsfr/theme/breadcrumb.html
mkdocs_dsfr/theme/dsfr_assets/artwork/background/ovoid.svg
mkdocs_dsfr/theme/dsfr_assets/artwork/dark.svg
mkdocs_dsfr/theme/dsfr_assets/artwork/light.svg
mkdocs_dsfr/theme/dsfr_assets/artwork/pictograms/buildings/city-hall.svg
mkdocs_dsfr/theme/dsfr_assets/artwork/pictograms/buildings/factory.svg
mkdocs_dsfr/theme/dsfr_assets/artwork/pictograms/buildings/house.svg
mkdocs_dsfr/theme/dsfr_assets/artwork/pictograms/buildings/nuclear-plant.svg
mkdocs_dsfr/theme/dsfr_assets/artwork/pictograms/buildings/school.svg
mkdocs_dsfr/theme/dsfr_assets/artwork/pictograms/digital/application.svg
mkdocs_dsfr/theme/dsfr_assets/artwork/pictograms/digital/avatar.svg
mkdocs_dsfr/theme/dsfr_assets/artwork/pictograms/digital/calendar.svg
mkdocs_dsfr/theme/dsfr_assets/artwork/pictograms/digital/coding.svg
mkdocs_dsfr/theme/dsfr_assets/artwork/pictograms/digital/data-visualization.svg
mkdocs_dsfr_men-0.5.2.dist-info/METADATA
mkdocs_dsfr_men-0.5.2.dist-info/WHEEL
mkdocs_dsfr_men-0.5.2.dist-info/entry_points.txt
mkdocs_dsfr_men-0.5.2.dist-info/licenses/LICENSE
mkdocs_dsfr_men-0.5.2.dist-info/RECORD
