Metadata-Version: 2.4
Name: mkdocs-dsfr-men
Version: 0.5.2
Summary: Système de Design Français (ou DSFR) sous forme de thème MkDocs
License-Expression: EUPL-1.2
License-File: LICENSE
Keywords: python,mkdocs,dsfr
Author: Philippe-André De Carvalho
Author-email: philippe-andre.de-carvalho@ac-orleans-tours.fr
Maintainer: Philippe-André De Carvalho
Maintainer-email: philippe-andre.de-carvalho@ac-orleans-tours.fr
Requires-Python: >=3.9,<4.0
Classifier: Development Status :: 3 - Alpha
Classifier: Environment :: Console
Classifier: Operating System :: OS Independent
Classifier: Intended Audience :: Developers
Classifier: Intended Audience :: Information Technology
Classifier: Intended Audience :: System Administrators
Classifier: Topic :: Software Development :: Build Tools
Classifier: Natural Language :: French
Classifier: Programming Language :: Python :: 3.9
Classifier: Programming Language :: Python :: 3.10
Classifier: Programming Language :: Python :: 3.11
Classifier: Programming Language :: Python :: 3.12
Classifier: Programming Language :: Python :: 3.13
Classifier: Topic :: Utilities
Classifier: Topic :: Software Development :: Documentation
Requires-Dist: beautifulsoup4 (>=4.13.3,<5.0.0)
Requires-Dist: jinja2 (>=3.1.6,<4.0.0)
Requires-Dist: mkdocs (>=1.6.1,<2.0.0)
Requires-Dist: pymdown-extensions (>=10.14.3,<11.0.0)
Requires-Dist: requests (>=2.32.4,<3.0.0)
Requires-Dist: urllib3 (>=2.5.0,<3.0.0)
Project-URL: Documentation, https://pages.mim-libre.fr/digital-commons/world/european-union/france/administration/education-nationale/projet/produit/mkdocs-dsfr
Project-URL: Homepage, https://gitlab.mim-libre.fr/digital-commons/world/european-union/france/administration/education-nationale/projet/produit/mkdocs-dsfr
Project-URL: Repository, https://gitlab.mim-libre.fr/digital-commons/world/european-union/france/administration/education-nationale/projet/produit/mkdocs-dsfr
